myhsisuseeid/__init__.py
myhsisuseeid/core.py
myhsisuseeid-0.1.1.dist-info/licenses/LICENSE.yaml
myhsisuseeid-0.1.1.dist-info/METADATA
myhsisuseeid-0.1.1.dist-info/WHEEL
myhsisuseeid-0.1.1.dist-info/top_level.txt
myhsisuseeid-0.1.1.dist-info/RECORD
