Metadata-Version: 2.4
Name: myhsisuseeid
Version: 0.1.1
Summary: مكتبة بايثون بسيطة تجريبية باسم myhsisuseeid
Author: اسمك هنا
Author-email: youremail@example.com
Requires-Python: >=3.6
License-File: LICENSE.yaml
Dynamic: author
Dynamic: author-email
Dynamic: license-file
Dynamic: requires-python
Dynamic: summary
